{
    "features": [
        {
            "geometry": {
                "coordinates": [
                    -116.740732772,
                    32.6188274509
                ],
                "type": "Point"
            },
            "identifiers": [
                {
                    "identifier": "f-mtssandiego-s-98121",
                    "tags": {
                        "intersection_code": "M-Street-E/B",
                        "location_type": "0",
                        "parent_station": "",
                        "reference_place": "",
                        "stop_code": "98121",
                        "stop_id": "98121",
                        "stop_lat": "32.6188274509",
                        "stop_lon": "-116.740732772",
                        "stop_name": "Hwy 94 & Summit Rd",
                        "stop_name_short": "Hwy 94&Summit",
                        "stop_place": "",
                        "wheelchair_boarding": "2"
                    }
                }
            ],
            "name": "Hwy 94 & Summit Rd",
            "onestopId": "s-9mucx6pfry-94~summit",
            "properties": {},
            "servedBy": [
                "o-9mu-mts"
            ],
            "tags": {},
            "type": "Feature"
        },
        {
            "geometry": {
                "coordinates": [
                    -116.741479682,
                    32.6188217251
                ],
                "type": "Point"
            },
            "identifiers": [
                {
                    "identifier": "f-mtssandiego-s-98122",
                    "tags": {
                        "intersection_code": "N-E/B",
                        "location_type": "0",
                        "parent_station": "",
                        "reference_place": "",
                        "stop_code": "98122",
                        "stop_id": "98122",
                        "stop_lat": "32.6188217251",
                        "stop_lon": "-116.741479682",
                        "stop_name": "Hwy 94 & Summit Rd",
                        "stop_name_short": "Hwy 94&Summit",
                        "stop_place": "",
                        "wheelchair_boarding": "2"
                    }
                }
            ],
            "name": "Hwy 94 & Summit Rd",
            "onestopId": "s-9mucx6p6qm-94~summit",
            "properties": {},
            "servedBy": [
                "o-9mu-mts"
            ],
            "tags": {},
            "type": "Feature"
        }
    ],
    "prefix": "9mucx",
    "properties": {},
    "type": "FeatureCollection"
}