{
    "features": [
        {
            "geometry": {
                "coordinates": [
                    -118.383896,
                    33.744778
                ],
                "type": "Point"
            },
            "identifiers": [
                {
                    "identifier": "f-9q5-lacmta-s-4262",
                    "tags": {
                        "location_type": "",
                        "parent_station": "",
                        "stop_code": "4262",
                        "stop_desc": "",
                        "stop_id": "4262",
                        "stop_lat": "33.744778",
                        "stop_lon": "-118.383896",
                        "stop_name": "Palos Verdes / Seacove",
                        "stop_url": "",
                        "tpis_name": ""
                    }
                }
            ],
            "name": "Palos Verdes / Seacove",
            "onestopId": "s-9mgzfp53x6-palosverdes~seacove",
            "properties": {},
            "servedBy": [
                "o-9q5-metrolosangeles"
            ],
            "tags": {},
            "type": "Feature"
        },
        {
            "geometry": {
                "coordinates": [
                    -118.38662,
                    33.745594
                ],
                "type": "Point"
            },
            "identifiers": [
                {
                    "identifier": "f-9q5-lacmta-s-4261",
                    "tags": {
                        "location_type": "",
                        "parent_station": "",
                        "stop_code": "4261",
                        "stop_desc": "",
                        "stop_id": "4261",
                        "stop_lat": "33.745594",
                        "stop_lon": "-118.38662",
                        "stop_name": "Palos Verdes / Barkentine",
                        "stop_url": "",
                        "tpis_name": ""
                    }
                }
            ],
            "name": "Palos Verdes / Barkentine",
            "onestopId": "s-9mgzfp1qrf-palosverdes~barkentine",
            "properties": {},
            "servedBy": [
                "o-9q5-metrolosangeles"
            ],
            "tags": {},
            "type": "Feature"
        },
        {
            "geometry": {
                "coordinates": [
                    -118.387039,
                    33.745205
                ],
                "type": "Point"
            },
            "identifiers": [
                {
                    "identifier": "f-9q5-lacmta-s-12754",
                    "tags": {
                        "location_type": "",
                        "parent_station": "",
                        "stop_code": "12754",
                        "stop_desc": "",
                        "stop_id": "12754",
                        "stop_lat": "33.745205",
                        "stop_lon": "-118.387039",
                        "stop_name": "Palos Verdes / Barkentine",
                        "stop_url": "",
                        "tpis_name": ""
                    }
                }
            ],
            "name": "Palos Verdes / Barkentine",
            "onestopId": "s-9mgzfp1hn4-palosverdes~barkentine",
            "properties": {},
            "servedBy": [
                "o-9q5-metrolosangeles"
            ],
            "tags": {},
            "type": "Feature"
        }
    ],
    "prefix": "9mgzf",
    "properties": {},
    "type": "FeatureCollection"
}