{
    "features": [
        {
            "geometry": {
                "coordinates": [
                    -116.43095054,
                    33.0695754691
                ],
                "type": "Point"
            },
            "identifiers": [
                {
                    "identifier": "f-mtssandiego-s-98008",
                    "tags": {
                        "intersection_code": "N-S/B",
                        "location_type": "0",
                        "parent_station": "",
                        "reference_place": "",
                        "stop_code": "98008",
                        "stop_id": "98008",
                        "stop_lat": "33.0695754691",
                        "stop_lon": "-116.43095054",
                        "stop_name": "Great Southern Overland Rte Of 1849 & Great Sandy ",
                        "stop_name_short": "Great Southern Overland Rte Of 1849&Great Sandy ",
                        "stop_place": "",
                        "wheelchair_boarding": "2"
                    }
                }
            ],
            "name": "Great Southern Overland Rte Of 1849 & Great Sandy ",
            "onestopId": "s-9mvhns1s4p-greatsouthernoverlandrteof1849~greatsandy",
            "properties": {},
            "servedBy": [
                "o-9mu-mts"
            ],
            "tags": {},
            "type": "Feature"
        },
        {
            "geometry": {
                "coordinates": [
                    -116.424577324,
                    33.0606303693
                ],
                "type": "Point"
            },
            "identifiers": [
                {
                    "identifier": "f-mtssandiego-s-98009",
                    "tags": {
                        "intersection_code": "M-Street-E/B",
                        "location_type": "0",
                        "parent_station": "",
                        "reference_place": "",
                        "stop_code": "98009",
                        "stop_id": "98009",
                        "stop_lat": "33.0606303693",
                        "stop_lon": "-116.424577324",
                        "stop_name": "Great Southern Overland Rte Of 1849 & Horse Camp C",
                        "stop_name_short": "Great Southern Overland Rte Of 1849&Horse Camp C",
                        "stop_place": "sheval",
                        "wheelchair_boarding": "2"
                    }
                }
            ],
            "name": "Great Southern Overland Rte Of 1849 & Horse Camp C",
            "onestopId": "s-9mvhndw0ns-greatsouthernoverlandrteof1849~horsecampc",
            "properties": {},
            "servedBy": [
                "o-9mu-mts"
            ],
            "tags": {},
            "type": "Feature"
        },
        {
            "geometry": {
                "coordinates": [
                    -116.43820836,
                    33.0778730246
                ],
                "type": "Point"
            },
            "identifiers": [
                {
                    "identifier": "f-mtssandiego-s-98007",
                    "tags": {
                        "intersection_code": "M-Street-S/B",
                        "location_type": "0",
                        "parent_station": "",
                        "reference_place": "",
                        "stop_code": "98007",
                        "stop_id": "98007",
                        "stop_lat": "33.0778730246",
                        "stop_lon": "-116.43820836",
                        "stop_name": "Great Southern Overland Rte Of 1849 & Shelter Vall",
                        "stop_name_short": "Great Southern Overland Rte Of 1849&Shelter Vall",
                        "stop_place": "",
                        "wheelchair_boarding": "2"
                    }
                }
            ],
            "name": "Great Southern Overland Rte Of 1849 & Shelter Vall",
            "onestopId": "s-9mvhnmsk94-greatsouthernoverlandrteof1849~sheltervall",
            "properties": {},
            "servedBy": [
                "o-9mu-mts"
            ],
            "tags": {},
            "type": "Feature"
        }
    ],
    "prefix": "9mvhn",
    "properties": {},
    "type": "FeatureCollection"
}