{"prefix": "9q9hx", "type": "FeatureCollection", "properties": {}, "features": [{"onestopId": "s-9q9hxhe7jx-sunnyvalecaltrain", "name": "Sunnyvale Caltrain", "tags": {}, "geometry": {"type": "Point", "coordinates": [-122.031423, 37.378789]}, "servedBy": ["o-9q9-caltrain"], "identifiers": [{"identifier": "f-caltrain-s-70222", "tags": {"stop_lat": "  37.378789", "stop_code": "70222", "stop_lon": "-122.031423", "parent_station": "ctsu", "stop_url": "", "stop_id": "70222", "stop_desc": "", "stop_name": "Sunnyvale Caltrain", "location_type": "0", "platform_code": "SB", "zone_id": "3"}}], "type": "Feature", "properties": {}}, {"onestopId": "s-9q9hxgh6ue-lawrencecaltrain", "name": "Lawrence Caltrain", "tags": {}, "geometry": {"type": "Point", "coordinates": [-121.997135, 37.370484]}, "servedBy": ["o-9q9-caltrain"], "identifiers": [{"identifier": "f-caltrain-s-70232", "tags": {"stop_lat": "  37.370484", "stop_code": "70232", "stop_lon": "-121.997135", "parent_station": "ctla", "stop_url": "", "stop_id": "70232", "stop_desc": "", "stop_name": "Lawrence Caltrain", "location_type": "0", "platform_code": "SB", "zone_id": "4"}}], "type": "Feature", "properties": {}}, {"onestopId": "s-9q9hxgh7t0-lawrencecaltrain", "name": "Lawrence Caltrain", "tags": {}, "geometry": {"type": "Point", "coordinates": [-121.997114, 37.370598]}, "servedBy": ["o-9q9-caltrain"], "identifiers": [{"identifier": "f-caltrain-s-70231", "tags": {"stop_lat": "  37.370598", "stop_code": "70231", "stop_lon": "-121.997114", "parent_station": "ctla", "stop_url": "", "stop_id": "70231", "stop_desc": "", "stop_name": "Lawrence Caltrain", "location_type": "0", "platform_code": "NB", "zone_id": "4"}}], "type": "Feature", "properties": {}}, {"onestopId": "s-9q9hxhe7yy-sunnyvalecaltrain", "name": "Sunnyvale Caltrain", "tags": {}, "geometry": {"type": "Point", "coordinates": [-122.031372, 37.378916]}, "servedBy": ["o-9q9-caltrain"], "identifiers": [{"identifier": "f-caltrain-s-70221", "tags": {"stop_lat": "  37.378916", "stop_code": "70221", "stop_lon": "-122.031372", "parent_station": "ctsu", "stop_url": "", "stop_id": "70221", "stop_desc": "", "stop_name": "Sunnyvale Caltrain", "location_type": "0", "platform_code": "NB", "zone_id": "3"}}], "type": "Feature", "properties": {}}]}