{"prefix": "9q9q6", "type": "FeatureCollection", "properties": {}, "features": [{"onestopId": "s-9q9q6p6u79-dublin~pleasanton", "name": "Dublin/Pleasanton", "tags": {}, "geometry": {"type": "Point", "coordinates": [-121.900367, 37.701695]}, "servedBy": ["o-9q9-bayarearapidtransit"], "identifiers": [{"identifier": "f-bart-s-DUBL", "tags": {"stop_lat": "37.701695", "zone_id": "DUBL", "stop_lon": "-121.900367", "stop_url": "http://www.bart.gov/stations/DUBL/", "stop_id": "DUBL", "stop_desc": "", "stop_name": "Dublin/Pleasanton"}}], "type": "Feature", "properties": {}}]}