{
    "features": [
        {
            "geometry": {
                "coordinates": [
                    -121.900367,
                    37.701695
                ],
                "type": "Point"
            },
            "identifiers": [
                "gtfs://f-9q9-bayarearapidtransit/s/DUBL"
            ],
            "name": "Dublin/Pleasanton",
            "onestopId": "s-9q9q6p6u-dublin~pleasanton",
            "properties": {},
            "servedBy": [
                "o-9q9-bayarearapidtransit"
            ],
            "tags": {},
            "type": "Feature"
        }
    ],
    "prefix": "9q9q6",
    "properties": {},
    "type": "FeatureCollection"
}