{"prefix": "9q9p1", "type": "FeatureCollection", "properties": {}, "features": [{"onestopId": "s-9q9p12qegh-oaklandferryterminal", "name": "Oakland Ferry Terminal", "tags": {}, "geometry": {"type": "Point", "coordinates": [-122.279758, 37.795011]}, "servedBy": ["o-9q8z-blue~goldfleet"], "identifiers": [{"identifier": "f-sfbayferries-s-1904", "tags": {"stop_lat": "37.795011", "stop_timezone": "", "stop_code": "", "stop_lon": "-122.279758", "parent_station": "", "stop_url": "", "stop_id": "1904", "stop_desc": "Oakland", "stop_name": "Oakland Ferry Terminal", "location_type": "0", "zone_id": "214"}}], "type": "Feature", "properties": {}}]}