{
    "features": [
        {
            "geometry": {
                "coordinates": [
                    -121.900367,
                    37.701695
                ],
                "type": "Point"
            },
            "identifiers": [
                {
                    "identifier": "f-bart-s-DUBL",
                    "tags": {
                        "stop_desc": "",
                        "stop_id": "DUBL",
                        "stop_lat": "37.701695",
                        "stop_lon": "-121.900367",
                        "stop_name": "Dublin/Pleasanton",
                        "stop_url": "http://www.bart.gov/stations/DUBL/",
                        "zone_id": "DUBL"
                    }
                }
            ],
            "name": "Dublin/Pleasanton",
            "onestopId": "s-9q9q6p6u79-dublin~pleasanton",
            "properties": {},
            "servedBy": [
                "o-9q9-bayarearapidtransit"
            ],
            "tags": {},
            "type": "Feature"
        }
    ],
    "prefix": "9q9q6",
    "properties": {},
    "type": "FeatureCollection"
}