{
    "features": [
        {
            "geometry": {
                "coordinates": [
                    -118.697823,
                    34.145962
                ],
                "type": "Point"
            },
            "identifiers": [
                {
                    "identifier": "f-9q5-lacmta-s-2855",
                    "tags": {
                        "location_type": "",
                        "parent_station": "",
                        "stop_code": "2855",
                        "stop_desc": "",
                        "stop_id": "2855",
                        "stop_lat": "34.145962",
                        "stop_lon": "-118.697823",
                        "stop_name": "Las Virgenes / Ventura Fwy On-Ramp",
                        "stop_url": "",
                        "tpis_name": ""
                    }
                }
            ],
            "name": "Las Virgenes / Ventura Fwy On-Ramp",
            "onestopId": "s-9q5d6bnfsk-lasvirgenes~venturafwyonramp",
            "properties": {},
            "servedBy": [
                "o-9q5-metrolosangeles"
            ],
            "tags": {},
            "type": "Feature"
        },
        {
            "geometry": {
                "coordinates": [
                    -118.698112,
                    34.149246
                ],
                "type": "Point"
            },
            "identifiers": [
                {
                    "identifier": "f-9q5-lacmta-s-20082",
                    "tags": {
                        "location_type": "",
                        "parent_station": "",
                        "stop_code": "20082",
                        "stop_desc": "",
                        "stop_id": "20082",
                        "stop_lat": "34.149246",
                        "stop_lon": "-118.698112",
                        "stop_name": "Las Virgenes / Ventura Fwy Overpass",
                        "stop_url": "",
                        "tpis_name": ""
                    }
                }
            ],
            "name": "Las Virgenes / Ventura Fwy Overpass",
            "onestopId": "s-9q5d6bwtv8-lasvirgenes~venturafwyoverpass",
            "properties": {},
            "servedBy": [
                "o-9q5-metrolosangeles"
            ],
            "tags": {},
            "type": "Feature"
        }
    ],
    "prefix": "9q5d6",
    "properties": {},
    "type": "FeatureCollection"
}