{
    "features": [
        {
            "geometry": {
                "coordinates": [
                    -122.056013,
                    37.928403
                ],
                "type": "Point"
            },
            "identifiers": [
                "gtfs://f-9q9-bayarearapidtransit/s/PHIL"
            ],
            "name": "Pleasant Hill/Contra Costa Centre",
            "onestopId": "s-9q9py89s-pleasanthill~contracostacentre",
            "properties": {},
            "servedBy": [
                "o-9q9-bayarearapidtransit"
            ],
            "tags": {},
            "type": "Feature"
        }
    ],
    "prefix": "9q9py",
    "properties": {},
    "type": "FeatureCollection"
}