{
    "features": [
        {
            "geometry": {
                "coordinates": [
                    -122.055306,
                    37.928768
                ],
                "type": "Point"
            },
            "identifiers": [
                {
                    "identifier": "f-f-actransit-s-9903190",
                    "tags": {
                        "location_type": "",
                        "parent_station": "",
                        "stop_code": "51431",
                        "stop_id": "9903190",
                        "stop_lat": "37.928768",
                        "stop_lon": "-122.055306",
                        "stop_name": "Pleasant Hill BART Station"
                    }
                }
            ],
            "name": "Pleasant Hill BART Station",
            "onestopId": "s-9q9py8dp14-pleasanthillbartstation",
            "properties": {},
            "servedBy": [
                "o-9q9-actransit"
            ],
            "tags": {},
            "type": "Feature"
        }
    ],
    "prefix": "9q9py",
    "properties": {},
    "type": "FeatureCollection"
}