{
    "features": [
        {
            "geometry": {
                "coordinates": [
                    -121.997135,
                    37.370484
                ],
                "type": "Point"
            },
            "identifiers": [
                "gtfs://f-9q9-caltrain/s/70232"
            ],
            "name": "Lawrence Caltrain",
            "onestopId": "s-9q9hxgh6-lawrencecaltrain",
            "properties": {},
            "servedBy": [
                "o-9q9-caltrain"
            ],
            "tags": {},
            "type": "Feature"
        },
        {
            "geometry": {
                "coordinates": [
                    -121.997114,
                    37.370598
                ],
                "type": "Point"
            },
            "identifiers": [
                "gtfs://f-9q9-caltrain/s/70231"
            ],
            "name": "Lawrence Caltrain",
            "onestopId": "s-9q9hxgh7-lawrencecaltrain",
            "properties": {},
            "servedBy": [
                "o-9q9-caltrain"
            ],
            "tags": {},
            "type": "Feature"
        },
        {
            "geometry": {
                "coordinates": [
                    -122.031372,
                    37.378916
                ],
                "type": "Point"
            },
            "identifiers": [
                "gtfs://f-9q9-caltrain/s/70221",
                "gtfs://f-9q9-caltrain/s/70222"
            ],
            "name": "Sunnyvale Caltrain",
            "onestopId": "s-9q9hxhe7-sunnyvalecaltrain",
            "properties": {},
            "servedBy": [
                "o-9q9-caltrain"
            ],
            "tags": {},
            "type": "Feature"
        }
    ],
    "prefix": "9q9hx",
    "properties": {},
    "type": "FeatureCollection"
}