{
    "features": [
        {
            "geometry": {
                "coordinates": [
                    -122.031423,
                    37.378789
                ],
                "type": "Point"
            },
            "identifiers": [
                {
                    "identifier": "f-caltrain-s-70222",
                    "tags": {
                        "location_type": "0",
                        "parent_station": "ctsu",
                        "platform_code": "SB",
                        "stop_code": "70222",
                        "stop_desc": "",
                        "stop_id": "70222",
                        "stop_lat": "  37.378789",
                        "stop_lon": "-122.031423",
                        "stop_name": "Sunnyvale Caltrain",
                        "stop_url": "",
                        "zone_id": "3"
                    }
                }
            ],
            "name": "Sunnyvale Caltrain",
            "onestopId": "s-9q9hxhe7jx-sunnyvalecaltrain",
            "properties": {},
            "servedBy": [
                "o-9q9-caltrain"
            ],
            "tags": {},
            "type": "Feature"
        },
        {
            "geometry": {
                "coordinates": [
                    -121.997135,
                    37.370484
                ],
                "type": "Point"
            },
            "identifiers": [
                {
                    "identifier": "f-caltrain-s-70232",
                    "tags": {
                        "location_type": "0",
                        "parent_station": "ctla",
                        "platform_code": "SB",
                        "stop_code": "70232",
                        "stop_desc": "",
                        "stop_id": "70232",
                        "stop_lat": "  37.370484",
                        "stop_lon": "-121.997135",
                        "stop_name": "Lawrence Caltrain",
                        "stop_url": "",
                        "zone_id": "4"
                    }
                }
            ],
            "name": "Lawrence Caltrain",
            "onestopId": "s-9q9hxgh6ue-lawrencecaltrain",
            "properties": {},
            "servedBy": [
                "o-9q9-caltrain"
            ],
            "tags": {},
            "type": "Feature"
        },
        {
            "geometry": {
                "coordinates": [
                    -121.997114,
                    37.370598
                ],
                "type": "Point"
            },
            "identifiers": [
                {
                    "identifier": "f-caltrain-s-70231",
                    "tags": {
                        "location_type": "0",
                        "parent_station": "ctla",
                        "platform_code": "NB",
                        "stop_code": "70231",
                        "stop_desc": "",
                        "stop_id": "70231",
                        "stop_lat": "  37.370598",
                        "stop_lon": "-121.997114",
                        "stop_name": "Lawrence Caltrain",
                        "stop_url": "",
                        "zone_id": "4"
                    }
                }
            ],
            "name": "Lawrence Caltrain",
            "onestopId": "s-9q9hxgh7t0-lawrencecaltrain",
            "properties": {},
            "servedBy": [
                "o-9q9-caltrain"
            ],
            "tags": {},
            "type": "Feature"
        },
        {
            "geometry": {
                "coordinates": [
                    -122.031372,
                    37.378916
                ],
                "type": "Point"
            },
            "identifiers": [
                {
                    "identifier": "f-caltrain-s-70221",
                    "tags": {
                        "location_type": "0",
                        "parent_station": "ctsu",
                        "platform_code": "NB",
                        "stop_code": "70221",
                        "stop_desc": "",
                        "stop_id": "70221",
                        "stop_lat": "  37.378916",
                        "stop_lon": "-122.031372",
                        "stop_name": "Sunnyvale Caltrain",
                        "stop_url": "",
                        "zone_id": "3"
                    }
                }
            ],
            "name": "Sunnyvale Caltrain",
            "onestopId": "s-9q9hxhe7yy-sunnyvalecaltrain",
            "properties": {},
            "servedBy": [
                "o-9q9-caltrain"
            ],
            "tags": {},
            "type": "Feature"
        }
    ],
    "prefix": "9q9hx",
    "properties": {},
    "type": "FeatureCollection"
}