{"prefix": "9q9n9", "type": "FeatureCollection", "properties": {}, "features": [{"onestopId": "s-9q9n9vxwbh-harborbay~ferryterminal", "name": "Harbor Bay Pkwy:Ferry Terminal", "tags": {}, "geometry": {"type": "Point", "coordinates": [-122.256544, 37.736475]}, "servedBy": ["o-9q9-actransit"], "identifiers": [{"identifier": "f-actransit-s-0101480", "tags": {"stop_lat": "37.736475", "stop_code": "58511", "stop_lon": "-122.256544", "parent_station": "place_HBFT", "stop_id": "0101480", "stop_name": "Harbor Bay Pkwy:Ferry Terminal", "location_type": ""}}], "type": "Feature", "properties": {}}]}