{"prefix": "9q9py", "type": "FeatureCollection", "properties": {}, "features": [{"onestopId": "s-9q9py8dp14-pleasanthillbartstation", "name": "Pleasant Hill BART Station", "tags": {}, "geometry": {"type": "Point", "coordinates": [-122.055306, 37.928768]}, "servedBy": ["o-9q9-actransit"], "identifiers": [{"identifier": "f-actransit-s-9903190", "tags": {"stop_lat": "37.928768", "stop_code": "51431", "stop_lon": "-122.055306", "parent_station": "", "stop_id": "9903190", "stop_name": "Pleasant Hill BART Station", "location_type": ""}}], "type": "Feature", "properties": {}}]}