{
    "features": [
        {
            "geometry": {
                "coordinates": [
                    -122.561378,
                    38.104431
                ],
                "type": "Point"
            },
            "identifiers": [
                {
                    "identifier": "f-goldengatetransit-s-41098",
                    "tags": {
                        "stop_code": "41098",
                        "stop_desc": "",
                        "stop_id": "41098",
                        "stop_lat": "  38.104431",
                        "stop_lon": "-122.561378",
                        "stop_name": "DeLong Av Bus Pad",
                        "zone_id": "4"
                    }
                }
            ],
            "name": "DeLong Av Bus Pad",
            "onestopId": "s-9qbbg09w2u-delongbuspad",
            "properties": {},
            "servedBy": [
                "o-9qb-goldengatetransit"
            ],
            "tags": {},
            "type": "Feature"
        },
        {
            "geometry": {
                "coordinates": [
                    -122.562752,
                    38.10466
                ],
                "type": "Point"
            },
            "identifiers": [
                {
                    "identifier": "f-goldengatetransit-s-41099",
                    "tags": {
                        "stop_code": "41099",
                        "stop_desc": "",
                        "stop_id": "41099",
                        "stop_lat": "  38.104660",
                        "stop_lon": "-122.562752",
                        "stop_name": "DeLong Av Bus Pad",
                        "zone_id": "4"
                    }
                }
            ],
            "name": "DeLong Av Bus Pad",
            "onestopId": "s-9qbbg08x8z-delongbuspad",
            "properties": {},
            "servedBy": [
                "o-9qb-goldengatetransit"
            ],
            "tags": {},
            "type": "Feature"
        }
    ],
    "prefix": "9qbbg",
    "properties": {},
    "type": "FeatureCollection"
}