{
    "features": [
        {
            "geometry": {
                "coordinates": [
                    -121.566225,
                    37.003485
                ],
                "type": "Point"
            },
            "identifiers": [
                "gtfs://f-9q9-caltrain/s/70322"
            ],
            "name": "Gilroy Caltrain",
            "onestopId": "s-9q9d98q0-gilroycaltrain",
            "properties": {},
            "servedBy": [
                "o-9q9-caltrain"
            ],
            "tags": {},
            "type": "Feature"
        },
        {
            "geometry": {
                "coordinates": [
                    -121.566088,
                    37.003538
                ],
                "type": "Point"
            },
            "identifiers": [
                "gtfs://f-9q9-caltrain/s/70321"
            ],
            "name": "Gilroy Caltrain",
            "onestopId": "s-9q9d98q3-gilroycaltrain",
            "properties": {},
            "servedBy": [
                "o-9q9-caltrain"
            ],
            "tags": {},
            "type": "Feature"
        }
    ],
    "prefix": "9q9d9",
    "properties": {},
    "type": "FeatureCollection"
}