{
    "features": [
        {
            "geometry": {
                "coordinates": [
                    -122.256544,
                    37.736475
                ],
                "type": "Point"
            },
            "identifiers": [
                {
                    "identifier": "f-f-actransit-s-0101480",
                    "tags": {
                        "location_type": "",
                        "parent_station": "place_HBFT",
                        "stop_code": "58511",
                        "stop_id": "0101480",
                        "stop_lat": "37.736475",
                        "stop_lon": "-122.256544",
                        "stop_name": "Harbor Bay Pkwy:Ferry Terminal"
                    }
                }
            ],
            "name": "Harbor Bay Pkwy:Ferry Terminal",
            "onestopId": "s-9q9n9vxwbh-harborbay~ferryterminal",
            "properties": {},
            "servedBy": [
                "o-9q9-actransit"
            ],
            "tags": {},
            "type": "Feature"
        }
    ],
    "prefix": "9q9n9",
    "properties": {},
    "type": "FeatureCollection"
}