{"prefix": "9qbbg", "type": "FeatureCollection", "properties": {}, "features": [{"onestopId": "s-9qbbg09w2u-delongbuspad", "name": "DeLong Av Bus Pad", "tags": {}, "geometry": {"type": "Point", "coordinates": [-122.561378, 38.104431]}, "servedBy": ["o-9qb-goldengatetransit"], "identifiers": [{"identifier": "f-goldengatetransit-s-41098", "tags": {"stop_lat": "  38.104431", "stop_code": "41098", "stop_lon": "-122.561378", "stop_id": "41098", "stop_desc": "", "stop_name": "DeLong Av Bus Pad", "zone_id": "4"}}], "type": "Feature", "properties": {}}, {"onestopId": "s-9qbbg08x8z-delongbuspad", "name": "DeLong Av Bus Pad", "tags": {}, "geometry": {"type": "Point", "coordinates": [-122.562752, 38.10466]}, "servedBy": ["o-9qb-goldengatetransit"], "identifiers": [{"identifier": "f-goldengatetransit-s-41099", "tags": {"stop_lat": "  38.104660", "stop_code": "41099", "stop_lon": "-122.562752", "stop_id": "41099", "stop_desc": "", "stop_name": "DeLong Av Bus Pad", "zone_id": "4"}}], "type": "Feature", "properties": {}}]}