{
    "features": [
        {
            "geometry": {
                "coordinates": [
                    -94.986966,
                    29.799263
                ],
                "type": "Point"
            },
            "identifiers": [
                {
                    "identifier": "f-9vk-mtaharriscounty-s-11605",
                    "tags": {
                        "location_type": "",
                        "parent_station": "",
                        "stop_code": "11605",
                        "stop_desc": "GARTH RD & INDEPENDENCE BLVD",
                        "stop_id": "11605",
                        "stop_lat": "29.799263",
                        "stop_lon": "-94.986966",
                        "stop_name": "BAYTOWN PR",
                        "stop_url": "",
                        "wheelchair_boarding": "0",
                        "zone_id": ""
                    }
                }
            ],
            "name": "BAYTOWN PR",
            "onestopId": "s-9vk3w8b973-baytownpr",
            "properties": {},
            "servedBy": [
                "o-9vk-metropolitantransitauthorityofharriscounty"
            ],
            "tags": {},
            "type": "Feature"
        }
    ],
    "prefix": "9vk3w",
    "properties": {},
    "type": "FeatureCollection"
}