{
    "features": [
        {
            "geometry": {
                "coordinates": [
                    -95.145096,
                    29.54346
                ],
                "type": "Point"
            },
            "identifiers": [
                {
                    "identifier": "f-mtaharriscounty-s-915",
                    "tags": {
                        "location_type": "",
                        "parent_station": "",
                        "stop_code": "915",
                        "stop_desc": "GULF FREEWAY & BAYBROOK MALL ST",
                        "stop_id": "915",
                        "stop_lat": "29.54346",
                        "stop_lon": "-95.145096",
                        "stop_name": "BAYBROOK MALL",
                        "stop_url": "",
                        "wheelchair_boarding": "0",
                        "zone_id": ""
                    }
                }
            ],
            "name": "BAYBROOK MALL",
            "onestopId": "s-9vk24fjrns-baybrookmall",
            "properties": {},
            "servedBy": [
                "o-9vk-metropolitantransitauthorityofharriscounty"
            ],
            "tags": {},
            "type": "Feature"
        }
    ],
    "prefix": "9vk24",
    "properties": {},
    "type": "FeatureCollection"
}