{
    "features": [
        {
            "geometry": {
                "coordinates": [
                    -122.669245,
                    49.042347
                ],
                "type": "Point"
            },
            "identifiers": [
                {
                    "identifier": "f-c28-translink-s-9024",
                    "tags": {
                        "location_type": "0",
                        "parent_station": "",
                        "stop_code": "58338",
                        "stop_desc": "200 ST @ 22 AVE",
                        "stop_id": "9024",
                        "stop_lat": "49.042347",
                        "stop_lon": "-122.669245",
                        "stop_name": "NB 200 ST FS 22 AV",
                        "stop_url": "",
                        "zone_id": "ZN 3"
                    }
                }
            ],
            "name": "NB 200 ST FS 22 AV",
            "onestopId": "s-c28ybxfurk-nb200fs22",
            "properties": {},
            "servedBy": [
                "o-c28-translink"
            ],
            "tags": {},
            "type": "Feature"
        },
        {
            "geometry": {
                "coordinates": [
                    -122.674191,
                    49.038376
                ],
                "type": "Point"
            },
            "identifiers": [
                {
                    "identifier": "f-c28-translink-s-9026",
                    "tags": {
                        "location_type": "0",
                        "parent_station": "",
                        "stop_code": "57123",
                        "stop_desc": "20 AVE @ 198 ST",
                        "stop_id": "9026",
                        "stop_lat": "49.038376",
                        "stop_lon": "-122.674191",
                        "stop_name": "EB 20 AV FS 198 ST",
                        "stop_url": "",
                        "zone_id": "ZN 3"
                    }
                }
            ],
            "name": "EB 20 AV FS 198 ST",
            "onestopId": "s-c28ybrpmhp-eb20fs198",
            "properties": {},
            "servedBy": [
                "o-c28-translink"
            ],
            "tags": {},
            "type": "Feature"
        },
        {
            "geometry": {
                "coordinates": [
                    -122.669248,
                    49.038776
                ],
                "type": "Point"
            },
            "identifiers": [
                {
                    "identifier": "f-c28-translink-s-9025",
                    "tags": {
                        "location_type": "0",
                        "parent_station": "",
                        "stop_code": "57124",
                        "stop_desc": "200 ST @ 20 AVE",
                        "stop_id": "9025",
                        "stop_lat": "49.038776",
                        "stop_lon": "-122.669248",
                        "stop_name": "NB 200 ST FS 20 AV",
                        "stop_url": "",
                        "zone_id": "ZN 3"
                    }
                }
            ],
            "name": "NB 200 ST FS 20 AV",
            "onestopId": "s-c28ybx4zx6-nb200fs20",
            "properties": {},
            "servedBy": [
                "o-c28-translink"
            ],
            "tags": {},
            "type": "Feature"
        }
    ],
    "prefix": "c28yb",
    "properties": {},
    "type": "FeatureCollection"
}