{
    "features": [
        {
            "geometry": {
                "coordinates": [
                    -122.183022,
                    47.7689896
                ],
                "type": "Point"
            },
            "identifiers": [
                {
                    "identifier": "f-c23-kingcounty-s-76234",
                    "tags": {
                        "location_type": "0",
                        "parent_station": "",
                        "stop_code": "",
                        "stop_desc": "",
                        "stop_id": "76234",
                        "stop_lat": "47.7689896",
                        "stop_lon": "-122.183022",
                        "stop_name": "NE 195th St & North Creek Pkwy",
                        "stop_timezone": "America/Los_Angeles",
                        "stop_url": "",
                        "zone_id": "19"
                    }
                }
            ],
            "name": "NE 195th St & North Creek Pkwy",
            "onestopId": "s-c23pg8j491-ne195th~northcreek",
            "properties": {},
            "servedBy": [
                "o-c23-metrotransit"
            ],
            "tags": {},
            "type": "Feature"
        },
        {
            "geometry": {
                "coordinates": [
                    -122.182404,
                    47.7691193
                ],
                "type": "Point"
            },
            "identifiers": [
                {
                    "identifier": "f-c23-kingcounty-s-76009",
                    "tags": {
                        "location_type": "0",
                        "parent_station": "",
                        "stop_code": "",
                        "stop_desc": "",
                        "stop_id": "76009",
                        "stop_lat": "47.7691193",
                        "stop_lon": "-122.182404",
                        "stop_name": "NE 195th St & 120th Ave NE",
                        "stop_timezone": "America/Los_Angeles",
                        "stop_url": "",
                        "zone_id": "19"
                    }
                }
            ],
            "name": "NE 195th St & 120th Ave NE",
            "onestopId": "s-c23pg8j7r9-ne195th~120thne",
            "properties": {},
            "servedBy": [
                "o-c23-metrotransit"
            ],
            "tags": {},
            "type": "Feature"
        },
        {
            "geometry": {
                "coordinates": [
                    -122.211502,
                    47.7939835
                ],
                "type": "Point"
            },
            "identifiers": [
                {
                    "identifier": "f-c23-kingcounty-s-76004",
                    "tags": {
                        "location_type": "0",
                        "parent_station": "",
                        "stop_code": "",
                        "stop_desc": "",
                        "stop_id": "76004",
                        "stop_lat": "47.7939835",
                        "stop_lon": "-122.211502",
                        "stop_name": "Canyon Park P&R & I-405",
                        "stop_timezone": "America/Los_Angeles",
                        "stop_url": "",
                        "zone_id": "17"
                    }
                }
            ],
            "name": "Canyon Park P&R & I-405",
            "onestopId": "s-c23pgh8k1s-canyonparkp~r~i405",
            "properties": {},
            "servedBy": [
                "o-c23-metrotransit"
            ],
            "tags": {},
            "type": "Feature"
        }
    ],
    "prefix": "c23pg",
    "properties": {},
    "type": "FeatureCollection"
}