{
    "features": [
        {
            "geometry": {
                "coordinates": [
                    -80.568001,
                    24.960387
                ],
                "type": "Point"
            },
            "identifiers": [
                {
                    "identifier": "f-miamidade-s-10368",
                    "tags": {
                        "location_type": "",
                        "parent_station": "",
                        "stop_code": "US#1M873",
                        "stop_desc": "",
                        "stop_id": "10368",
                        "stop_lat": "24.960387",
                        "stop_lon": "-80.568001",
                        "stop_name": "US 1@MM 87 TAVERNIER",
                        "stop_url": "",
                        "wheelchair_boarding": "0",
                        "zone_id": ""
                    }
                }
            ],
            "name": "US 1@MM 87 TAVERNIER",
            "onestopId": "s-dhqtyxuhv9-us1~mm87tavernier",
            "properties": {},
            "servedBy": [
                "o-dhw-miamidadetransit"
            ],
            "tags": {},
            "type": "Feature"
        },
        {
            "geometry": {
                "coordinates": [
                    -80.568438,
                    24.959922
                ],
                "type": "Point"
            },
            "identifiers": [
                {
                    "identifier": "f-miamidade-s-10369",
                    "tags": {
                        "location_type": "",
                        "parent_station": "",
                        "stop_code": "US#1M871",
                        "stop_desc": "STATE HWY 5 & OVERSEAS HWY",
                        "stop_id": "10369",
                        "stop_lat": "24.959922",
                        "stop_lon": "-80.568438",
                        "stop_name": "US 1@MM 87 TAVERNIER",
                        "stop_url": "",
                        "wheelchair_boarding": "0",
                        "zone_id": ""
                    }
                }
            ],
            "name": "US 1@MM 87 TAVERNIER",
            "onestopId": "s-dhqtyxgf56-us1~mm87tavernier",
            "properties": {},
            "servedBy": [
                "o-dhw-miamidadetransit"
            ],
            "tags": {},
            "type": "Feature"
        }
    ],
    "prefix": "dhqty",
    "properties": {},
    "type": "FeatureCollection"
}