{
    "features": [
        {
            "geometry": {
                "coordinates": [
                    -80.198082,
                    25.972122
                ],
                "type": "Point"
            },
            "identifiers": [
                {
                    "identifier": "f-dhw-miamidade-s-5764",
                    "tags": {
                        "location_type": "",
                        "parent_station": "",
                        "stop_code": "A2AV2141",
                        "stop_desc": "",
                        "stop_id": "5764",
                        "stop_lat": "25.972122",
                        "stop_lon": "-80.198082",
                        "stop_name": "NE 2 AV@NE 214 ST",
                        "stop_url": "",
                        "wheelchair_boarding": "0",
                        "zone_id": ""
                    }
                }
            ],
            "name": "NE 2 AV@NE 214 ST",
            "onestopId": "s-dhwgz01d94-ne2~ne214",
            "properties": {},
            "servedBy": [
                "o-dhw-miamidadetransit"
            ],
            "tags": {},
            "type": "Feature"
        }
    ],
    "prefix": "dhwgz",
    "properties": {},
    "type": "FeatureCollection"
}