{
    "features": [
        {
            "geometry": {
                "coordinates": [
                    -80.154718,
                    25.713721
                ],
                "type": "Point"
            },
            "identifiers": [
                {
                    "identifier": "f-miamidade-s-4362",
                    "tags": {
                        "location_type": "",
                        "parent_station": "",
                        "stop_code": "CRDBCRA4",
                        "stop_desc": "",
                        "stop_id": "4362",
                        "stop_lat": "25.713721",
                        "stop_lon": "-80.154718",
                        "stop_name": "CRANDON BD@CRANDON GOLF COURSE",
                        "stop_url": "",
                        "wheelchair_boarding": "0",
                        "zone_id": ""
                    }
                }
            ],
            "name": "CRANDON BD@CRANDON GOLF COURSE",
            "onestopId": "s-dhx4211179-crandonbd~crandongolfcourse",
            "properties": {},
            "servedBy": [
                "o-dhw-miamidadetransit"
            ],
            "tags": {},
            "type": "Feature"
        },
        {
            "geometry": {
                "coordinates": [
                    -80.154057,
                    25.725976
                ],
                "type": "Point"
            },
            "identifiers": [
                {
                    "identifier": "f-miamidade-s-4361",
                    "tags": {
                        "location_type": "",
                        "parent_station": "",
                        "stop_code": "CRDBSUN4",
                        "stop_desc": "CRANDON BD & SUNDAYS ON THE BAY",
                        "stop_id": "4361",
                        "stop_lat": "25.725976",
                        "stop_lon": "-80.154057",
                        "stop_name": "CRANDON BD@CRANDON PARK MARINA",
                        "stop_url": "",
                        "wheelchair_boarding": "0",
                        "zone_id": ""
                    }
                }
            ],
            "name": "CRANDON BD@CRANDON PARK MARINA",
            "onestopId": "s-dhx42538ej-crandonbd~crandonparkmarina",
            "properties": {},
            "servedBy": [
                "o-dhw-miamidadetransit"
            ],
            "tags": {},
            "type": "Feature"
        },
        {
            "geometry": {
                "coordinates": [
                    -80.153519,
                    25.714681
                ],
                "type": "Point"
            },
            "identifiers": [
                {
                    "identifier": "f-miamidade-s-4366",
                    "tags": {
                        "location_type": "",
                        "parent_station": "",
                        "stop_code": "CRDBLNK2",
                        "stop_desc": "",
                        "stop_id": "4366",
                        "stop_lat": "25.714681",
                        "stop_lon": "-80.153519",
                        "stop_name": "CRANDON BD@OP LINKS AT KEY BISC",
                        "stop_url": "",
                        "wheelchair_boarding": "0",
                        "zone_id": ""
                    }
                }
            ],
            "name": "CRANDON BD@OP LINKS AT KEY BISC",
            "onestopId": "s-dhx4211yze-crandonbd~oplinksatkeybisc",
            "properties": {},
            "servedBy": [
                "o-dhw-miamidadetransit"
            ],
            "tags": {},
            "type": "Feature"
        },
        {
            "geometry": {
                "coordinates": [
                    -80.15371,
                    25.726206
                ],
                "type": "Point"
            },
            "identifiers": [
                {
                    "identifier": "f-miamidade-s-4367",
                    "tags": {
                        "location_type": "",
                        "parent_station": "",
                        "stop_code": "CRDBOSN2",
                        "stop_desc": "",
                        "stop_id": "4367",
                        "stop_lat": "25.726206",
                        "stop_lon": "-80.15371",
                        "stop_name": "CRANDON BD@OP SUNDAYS ON BAY",
                        "stop_url": "",
                        "wheelchair_boarding": "0",
                        "zone_id": ""
                    }
                }
            ],
            "name": "CRANDON BD@OP SUNDAYS ON BAY",
            "onestopId": "s-dhx4253f50-crandonbd~opsundaysonbay",
            "properties": {},
            "servedBy": [
                "o-dhw-miamidadetransit"
            ],
            "tags": {},
            "type": "Feature"
        }
    ],
    "prefix": "dhx42",
    "properties": {},
    "type": "FeatureCollection"
}