{
    "features": [
        {
            "geometry": {
                "coordinates": [
                    -80.46552,
                    25.676657
                ],
                "type": "Point"
            },
            "identifiers": [
                {
                    "identifier": "f-dhw-miamidade-s-9904",
                    "tags": {
                        "location_type": "",
                        "parent_station": "",
                        "stop_code": "C16796S3",
                        "stop_desc": "",
                        "stop_id": "9904",
                        "stop_lat": "25.676657",
                        "stop_lon": "-80.46552",
                        "stop_name": "SW 167 AV@SW 96 ST",
                        "stop_url": "",
                        "wheelchair_boarding": "0",
                        "zone_id": ""
                    }
                }
            ],
            "name": "SW 167 AV@SW 96 ST",
            "onestopId": "s-dhwf0fqc37-sw167~sw96",
            "properties": {},
            "servedBy": [
                "o-dhw-miamidadetransit"
            ],
            "tags": {},
            "type": "Feature"
        },
        {
            "geometry": {
                "coordinates": [
                    -80.465498,
                    25.671054
                ],
                "type": "Point"
            },
            "identifiers": [
                {
                    "identifier": "f-dhw-miamidade-s-3421",
                    "tags": {
                        "location_type": "",
                        "parent_station": "",
                        "stop_code": "C1671032",
                        "stop_desc": "",
                        "stop_id": "3421",
                        "stop_lat": "25.671054",
                        "stop_lon": "-80.465498",
                        "stop_name": "SW 167 AV@OP # 10300 CARROLL HS",
                        "stop_url": "",
                        "wheelchair_boarding": "0",
                        "zone_id": ""
                    }
                }
            ],
            "name": "SW 167 AV@OP # 10300 CARROLL HS",
            "onestopId": "s-dhwf0cqb9z-sw167~op10300carrollhs",
            "properties": {},
            "servedBy": [
                "o-dhw-miamidadetransit"
            ],
            "tags": {},
            "type": "Feature"
        },
        {
            "geometry": {
                "coordinates": [
                    -80.465752,
                    25.670442
                ],
                "type": "Point"
            },
            "identifiers": [
                {
                    "identifier": "f-dhw-miamidade-s-3408",
                    "tags": {
                        "location_type": "",
                        "parent_station": "",
                        "stop_code": "C1671034",
                        "stop_desc": "",
                        "stop_id": "3408",
                        "stop_lat": "25.670442",
                        "stop_lon": "-80.465752",
                        "stop_name": "SW 167 AV@# 10300 CARROLL HS",
                        "stop_url": "",
                        "wheelchair_boarding": "0",
                        "zone_id": ""
                    }
                }
            ],
            "name": "SW 167 AV@# 10300 CARROLL HS",
            "onestopId": "s-dhwf0cnthj-sw167~10300carrollhs",
            "properties": {},
            "servedBy": [
                "o-dhw-miamidadetransit"
            ],
            "tags": {},
            "type": "Feature"
        },
        {
            "geometry": {
                "coordinates": [
                    -80.465365,
                    25.676757
                ],
                "type": "Point"
            },
            "identifiers": [
                {
                    "identifier": "f-dhw-miamidade-s-9905",
                    "tags": {
                        "location_type": "",
                        "parent_station": "",
                        "stop_code": "C16796S2",
                        "stop_desc": "",
                        "stop_id": "9905",
                        "stop_lat": "25.676757",
                        "stop_lon": "-80.465365",
                        "stop_name": "SW 167 AV@SW 96 ST",
                        "stop_url": "",
                        "wheelchair_boarding": "0",
                        "zone_id": ""
                    }
                }
            ],
            "name": "SW 167 AV@SW 96 ST",
            "onestopId": "s-dhwf0fqcvn-sw167~sw96",
            "properties": {},
            "servedBy": [
                "o-dhw-miamidadetransit"
            ],
            "tags": {},
            "type": "Feature"
        }
    ],
    "prefix": "dhwf0",
    "properties": {},
    "type": "FeatureCollection"
}