{
    "features": [
        {
            "geometry": {
                "coordinates": [
                    -81.075625,
                    24.716268
                ],
                "type": "Point"
            },
            "identifiers": [
                {
                    "identifier": "f-miamidade-s-9843",
                    "tags": {
                        "location_type": "",
                        "parent_station": "",
                        "stop_code": "US#1M503",
                        "stop_desc": "CONNECTING RD & OVERSEAS HWY",
                        "stop_id": "9843",
                        "stop_lat": "24.716268",
                        "stop_lon": "-81.075625",
                        "stop_name": "US 1@MM 50 MARATHON",
                        "stop_url": "",
                        "wheelchair_boarding": "0",
                        "zone_id": ""
                    }
                }
            ],
            "name": "US 1@MM 50 MARATHON",
            "onestopId": "s-dhqke56w9n-us1~mm50marathon",
            "properties": {},
            "servedBy": [
                "o-dhw-miamidadetransit"
            ],
            "tags": {},
            "type": "Feature"
        },
        {
            "geometry": {
                "coordinates": [
                    -81.075723,
                    24.71614
                ],
                "type": "Point"
            },
            "identifiers": [
                {
                    "identifier": "f-miamidade-s-9844",
                    "tags": {
                        "location_type": "",
                        "parent_station": "",
                        "stop_code": "US#1M501",
                        "stop_desc": "STATE HWY 5 & CONNECTING RD",
                        "stop_id": "9844",
                        "stop_lat": "24.71614",
                        "stop_lon": "-81.075723",
                        "stop_name": "US 1@MM 50 MARATHON",
                        "stop_url": "",
                        "wheelchair_boarding": "0",
                        "zone_id": ""
                    }
                }
            ],
            "name": "US 1@MM 50 MARATHON",
            "onestopId": "s-dhqke56myw-us1~mm50marathon",
            "properties": {},
            "servedBy": [
                "o-dhw-miamidadetransit"
            ],
            "tags": {},
            "type": "Feature"
        }
    ],
    "prefix": "dhqke",
    "properties": {},
    "type": "FeatureCollection"
}