{
    "features": [
        {
            "geometry": {
                "coordinates": [
                    -80.167774,
                    26.031717
                ],
                "type": "Point"
            },
            "identifiers": [
                {
                    "identifier": "f-miamidade-s-10377",
                    "tags": {
                        "location_type": "",
                        "parent_station": "",
                        "stop_code": "SHERTRRT",
                        "stop_desc": "PARKING LOT",
                        "stop_id": "10377",
                        "stop_lat": "26.031717",
                        "stop_lon": "-80.167774",
                        "stop_name": "SHERIDAN STREET TRI-RAIL STATION",
                        "stop_url": "",
                        "wheelchair_boarding": "0",
                        "zone_id": ""
                    }
                }
            ],
            "name": "SHERIDAN STREET TRI-RAIL STATION",
            "onestopId": "s-dhwupdzter-sheridantrirailstation",
            "properties": {},
            "servedBy": [
                "o-dhw-miamidadetransit"
            ],
            "tags": {},
            "type": "Feature"
        }
    ],
    "prefix": "dhwup",
    "properties": {},
    "type": "FeatureCollection"
}