{
    "features": [
        {
            "geometry": {
                "coordinates": [
                    -84.214645,
                    33.704633
                ],
                "type": "Point"
            },
            "identifiers": [
                {
                    "identifier": "f-marta-s-210132",
                    "tags": {
                        "stop_code": "210132",
                        "stop_id": "210132",
                        "stop_lat": "33.704633",
                        "stop_lon": "-84.214645",
                        "stop_name": "PLEASANTWOOD DR @ SNAPFINGER RD"
                    }
                }
            ],
            "name": "PLEASANTWOOD DR @ SNAPFINGER RD",
            "onestopId": "s-djupexsz8w-pleasantwood~snapfinger",
            "properties": {},
            "servedBy": [
                "o-dnh-metropolitanatlantarapidtransitauthority"
            ],
            "tags": {},
            "type": "Feature"
        },
        {
            "geometry": {
                "coordinates": [
                    -84.214235,
                    33.7052
                ],
                "type": "Point"
            },
            "identifiers": [
                {
                    "identifier": "f-marta-s-131158",
                    "tags": {
                        "stop_code": "131158",
                        "stop_id": "131158",
                        "stop_lat": "33.7052",
                        "stop_lon": "-84.214235",
                        "stop_name": "PLEASANTWOOD DR@SNAPFINGER RD"
                    }
                }
            ],
            "name": "PLEASANTWOOD DR@SNAPFINGER RD",
            "onestopId": "s-djupexv540-pleasantwood~snapfinger",
            "properties": {},
            "servedBy": [
                "o-dnh-metropolitanatlantarapidtransitauthority"
            ],
            "tags": {},
            "type": "Feature"
        }
    ],
    "prefix": "djupe",
    "properties": {},
    "type": "FeatureCollection"
}