{
    "features": [
        {
            "geometry": {
                "coordinates": [
                    -79.540672,
                    43.592732
                ],
                "type": "Point"
            },
            "identifiers": [
                {
                    "identifier": "f-dpz8-ttc-s-15037",
                    "tags": {
                        "location_type": "",
                        "parent_station": "",
                        "stop_code": "15223",
                        "stop_desc": "",
                        "stop_id": "15037",
                        "stop_lat": "43.592732",
                        "stop_lon": "-79.540672",
                        "stop_name": "LAKE SHORE BLVD WEST AT THIRTY NINTH ST",
                        "stop_url": "",
                        "wheelchair_boarding": "2",
                        "zone_id": ""
                    }
                }
            ],
            "name": "LAKE SHORE BLVD WEST AT THIRTY NINTH ST",
            "onestopId": "s-dpxrypb604-lakeshorewestatthirtyninth",
            "properties": {},
            "servedBy": [
                "o-dpz8-ttc"
            ],
            "tags": {},
            "type": "Feature"
        },
        {
            "geometry": {
                "coordinates": [
                    -79.538224,
                    43.593354
                ],
                "type": "Point"
            },
            "identifiers": [
                {
                    "identifier": "f-dpz8-ttc-s-1073",
                    "tags": {
                        "location_type": "",
                        "parent_station": "",
                        "stop_code": "5164",
                        "stop_desc": "",
                        "stop_id": "1073",
                        "stop_lat": "43.593354",
                        "stop_lon": "-79.538224",
                        "stop_name": "LAKE SHORE BLVD WEST AT THIRTY SEVENTH ST",
                        "stop_url": "",
                        "wheelchair_boarding": "2",
                        "zone_id": ""
                    }
                }
            ],
            "name": "LAKE SHORE BLVD WEST AT THIRTY SEVENTH ST",
            "onestopId": "s-dpxrypfj9n-lakeshorewestatthirtyseventh",
            "properties": {},
            "servedBy": [
                "o-dpz8-ttc"
            ],
            "tags": {},
            "type": "Feature"
        },
        {
            "geometry": {
                "coordinates": [
                    -79.539331,
                    43.59335
                ],
                "type": "Point"
            },
            "identifiers": [
                {
                    "identifier": "f-dpz8-ttc-s-2527",
                    "tags": {
                        "location_type": "",
                        "parent_station": "",
                        "stop_code": "3386",
                        "stop_desc": "",
                        "stop_id": "2527",
                        "stop_lat": "43.59335",
                        "stop_lon": "-79.539331",
                        "stop_name": "BROWNS LINE AT LAKE SHORE BLVD WEST NORTH SIDE",
                        "stop_url": "",
                        "wheelchair_boarding": "1",
                        "zone_id": ""
                    }
                }
            ],
            "name": "BROWNS LINE AT LAKE SHORE BLVD WEST NORTH SIDE",
            "onestopId": "s-dpxrypcjxm-brownslineatlakeshorewestnorthside",
            "properties": {},
            "servedBy": [
                "o-dpz8-ttc"
            ],
            "tags": {},
            "type": "Feature"
        },
        {
            "geometry": {
                "coordinates": [
                    -79.537983,
                    43.59349
                ],
                "type": "Point"
            },
            "identifiers": [
                {
                    "identifier": "f-dpz8-ttc-s-8445",
                    "tags": {
                        "location_type": "",
                        "parent_station": "",
                        "stop_code": "5165",
                        "stop_desc": "",
                        "stop_id": "8445",
                        "stop_lat": "43.59349",
                        "stop_lon": "-79.537983",
                        "stop_name": "LAKE SHORE BLVD WEST AT THIRTY SEVENTH ST",
                        "stop_url": "",
                        "wheelchair_boarding": "2",
                        "zone_id": ""
                    }
                }
            ],
            "name": "LAKE SHORE BLVD WEST AT THIRTY SEVENTH ST",
            "onestopId": "s-dpxrypfnqx-lakeshorewestatthirtyseventh",
            "properties": {},
            "servedBy": [
                "o-dpz8-ttc"
            ],
            "tags": {},
            "type": "Feature"
        }
    ],
    "prefix": "dpxry",
    "properties": {},
    "type": "FeatureCollection"
}