{
    "features": [
        {
            "geometry": {
                "coordinates": [
                    -79.264333,
                    43.901661
                ],
                "type": "Point"
            },
            "identifiers": [
                {
                    "identifier": "f-ttc-s-3668",
                    "tags": {
                        "location_type": "",
                        "parent_station": "",
                        "stop_code": "13649",
                        "stop_desc": "",
                        "stop_id": "3668",
                        "stop_lat": "43.901661",
                        "stop_lon": "-79.264333",
                        "stop_name": "105 ANDERSON AVE",
                        "stop_url": "",
                        "wheelchair_boarding": "1",
                        "zone_id": ""
                    }
                }
            ],
            "name": "105 ANDERSON AVE",
            "onestopId": "s-dpz9u213xn-105anderson",
            "properties": {},
            "servedBy": [
                "o-dpz8-ttc"
            ],
            "tags": {},
            "type": "Feature"
        },
        {
            "geometry": {
                "coordinates": [
                    -79.266724,
                    43.904382
                ],
                "type": "Point"
            },
            "identifiers": [
                {
                    "identifier": "f-ttc-s-1611",
                    "tags": {
                        "location_type": "",
                        "parent_station": "",
                        "stop_code": "13652",
                        "stop_desc": "",
                        "stop_id": "1611",
                        "stop_lat": "43.904382",
                        "stop_lon": "-79.266724",
                        "stop_name": "CASTLEMORE AVE AT MARKHAM RD",
                        "stop_url": "",
                        "wheelchair_boarding": "1",
                        "zone_id": ""
                    }
                }
            ],
            "name": "CASTLEMORE AVE AT MARKHAM RD",
            "onestopId": "s-dpz9u0x9x6-castlemoreatmarkham",
            "properties": {},
            "servedBy": [
                "o-dpz8-ttc"
            ],
            "tags": {},
            "type": "Feature"
        },
        {
            "geometry": {
                "coordinates": [
                    -79.264564,
                    43.904019
                ],
                "type": "Point"
            },
            "identifiers": [
                {
                    "identifier": "f-ttc-s-8635",
                    "tags": {
                        "location_type": "",
                        "parent_station": "",
                        "stop_code": "13650",
                        "stop_desc": "",
                        "stop_id": "8635",
                        "stop_lat": "43.904019",
                        "stop_lon": "-79.264564",
                        "stop_name": "ANDERSON AVE AT CASTLEMORE AVE",
                        "stop_url": "",
                        "wheelchair_boarding": "2",
                        "zone_id": ""
                    }
                }
            ],
            "name": "ANDERSON AVE AT CASTLEMORE AVE",
            "onestopId": "s-dpz9u23r3y-andersonatcastlemore",
            "properties": {},
            "servedBy": [
                "o-dpz8-ttc"
            ],
            "tags": {},
            "type": "Feature"
        }
    ],
    "prefix": "dpz9u",
    "properties": {},
    "type": "FeatureCollection"
}