{
    "features": [
        {
            "geometry": {
                "coordinates": [
                    -78.933181,
                    39.648902
                ],
                "type": "Point"
            },
            "identifiers": [
                {
                    "identifier": "f-dq-mtamaryland-s-FRSTBG",
                    "tags": {
                        "location_type": "",
                        "parent_station": "",
                        "stop_code": "",
                        "stop_desc": "Allegany County Transit service available here, and stop is at the Cordts PE Center",
                        "stop_id": "FRSTBG",
                        "stop_lat": "39.648902",
                        "stop_lon": "-78.933181",
                        "stop_name": "Frostburg State University",
                        "stop_url": "",
                        "wheelchair_boarding": "",
                        "zone_id": ""
                    }
                }
            ],
            "name": "Frostburg State University",
            "onestopId": "s-dppcecfeee-frostburgstateuniversity",
            "properties": {},
            "servedBy": [
                "o-dq-mtaofficeoflocaltransitsupport"
            ],
            "tags": {},
            "type": "Feature"
        }
    ],
    "prefix": "dppce",
    "properties": {},
    "type": "FeatureCollection"
}