{
    "features": [
        {
            "geometry": {
                "coordinates": [
                    -76.042425,
                    38.553175
                ],
                "type": "Point"
            },
            "identifiers": [
                {
                    "identifier": "f-dq-mtamaryland-s-CMBRG",
                    "tags": {
                        "location_type": "",
                        "parent_station": "",
                        "stop_code": "",
                        "stop_desc": "CITGO GAS",
                        "stop_id": "CMBRG",
                        "stop_lat": "38.553175",
                        "stop_lon": "-76.042425",
                        "stop_name": "Cambridge",
                        "stop_url": "",
                        "wheelchair_boarding": "",
                        "zone_id": ""
                    }
                }
            ],
            "name": "Cambridge",
            "onestopId": "s-dqcgmd7se0-cambridge",
            "properties": {},
            "servedBy": [
                "o-dq-mtaofficeoflocaltransitsupport"
            ],
            "tags": {},
            "type": "Feature"
        }
    ],
    "prefix": "dqcgm",
    "properties": {},
    "type": "FeatureCollection"
}