{
    "features": [
        {
            "geometry": {
                "coordinates": [
                    -75.747803,
                    38.462083
                ],
                "type": "Point"
            },
            "identifiers": [
                {
                    "identifier": "f-mtamaryland-s-MRDL_SPGS",
                    "tags": {
                        "location_type": "",
                        "parent_station": "",
                        "stop_code": "",
                        "stop_desc": "Mardela Goose Creek",
                        "stop_id": "MRDL_SPGS",
                        "stop_lat": "38.462083",
                        "stop_lon": "-75.747803",
                        "stop_name": "Mardela Springs",
                        "stop_url": "",
                        "wheelchair_boarding": "",
                        "zone_id": ""
                    }
                }
            ],
            "name": "Mardela Springs",
            "onestopId": "s-dqf4u3f1u7-mardelasprings",
            "properties": {},
            "servedBy": [
                "o-dq-mtaofficeoflocaltransitsupport"
            ],
            "tags": {},
            "type": "Feature"
        }
    ],
    "prefix": "dqf4u",
    "properties": {},
    "type": "FeatureCollection"
}