{
    "features": [
        {
            "geometry": {
                "coordinates": [
                    -76.059854,
                    38.778527
                ],
                "type": "Point"
            },
            "identifiers": [
                {
                    "identifier": "f-mtamaryland-s-EASTN",
                    "tags": {
                        "location_type": "",
                        "parent_station": "",
                        "stop_code": "",
                        "stop_desc": "Easton Sunoco",
                        "stop_id": "EASTN",
                        "stop_lat": "38.778527",
                        "stop_lon": "-76.059854",
                        "stop_name": "Easton",
                        "stop_url": "",
                        "wheelchair_boarding": "",
                        "zone_id": ""
                    }
                }
            ],
            "name": "Easton",
            "onestopId": "s-dqcut5qvkc-easton",
            "properties": {},
            "servedBy": [
                "o-dq-mtaofficeoflocaltransitsupport"
            ],
            "tags": {},
            "type": "Feature"
        }
    ],
    "prefix": "dqcut",
    "properties": {},
    "type": "FeatureCollection"
}