{
    "features": [
        {
            "geometry": {
                "coordinates": [
                    -76.905635,
                    38.563477
                ],
                "type": "Point"
            },
            "identifiers": [
                {
                    "identifier": "f-dq-mtamaryland-s-12540",
                    "tags": {
                        "location_type": "",
                        "parent_station": "",
                        "stop_code": "12540",
                        "stop_desc": "PINEY CHURCH RD at FORGOTTEN FARM PL",
                        "stop_id": "12540",
                        "stop_lat": "38.563477",
                        "stop_lon": "-76.905635",
                        "stop_name": "SOUTHERN MARYLAND BLUE CRABS STADIUM",
                        "stop_url": "",
                        "wheelchair_boarding": "0",
                        "zone_id": ""
                    }
                }
            ],
            "name": "SOUTHERN MARYLAND BLUE CRABS STADIUM",
            "onestopId": "s-dqc73ur08c-southernmarylandbluecrabsstadium",
            "properties": {},
            "servedBy": [
                "o-dqc-marylandtransitadministration"
            ],
            "tags": {},
            "type": "Feature"
        }
    ],
    "prefix": "dqc73",
    "properties": {},
    "type": "FeatureCollection"
}