{
    "features": [
        {
            "geometry": {
                "coordinates": [
                    -77.134985,
                    39.022556
                ],
                "type": "Point"
            },
            "identifiers": [
                {
                    "identifier": "f-dq-mtamaryland-s-11921",
                    "tags": {
                        "location_type": "",
                        "parent_station": "",
                        "stop_code": "11921",
                        "stop_desc": "",
                        "stop_id": "11921",
                        "stop_lat": "39.022556",
                        "stop_lon": "-77.134985",
                        "stop_name": "FERNWOOD RD & CAMALIER BLDG nb",
                        "stop_url": "",
                        "wheelchair_boarding": "0",
                        "zone_id": ""
                    }
                }
            ],
            "name": "FERNWOOD RD & CAMALIER BLDG nb",
            "onestopId": "s-dqcjuzb4be-fernwood~camalierbldgnb",
            "properties": {},
            "servedBy": [
                "o-dqc-marylandtransitadministration"
            ],
            "tags": {},
            "type": "Feature"
        }
    ],
    "prefix": "dqcju",
    "properties": {},
    "type": "FeatureCollection"
}