{
    "features": [
        {
            "geometry": {
                "coordinates": [
                    -76.532567,
                    38.706613
                ],
                "type": "Point"
            },
            "identifiers": [
                {
                    "identifier": "f-mtamaryland-s-11616",
                    "tags": {
                        "location_type": "",
                        "parent_station": "",
                        "stop_code": "11616",
                        "stop_desc": "CHESAPEAKE AVE at 4TH ST",
                        "stop_id": "11616",
                        "stop_lat": "38.706613",
                        "stop_lon": "-76.532567",
                        "stop_name": "NORTH BEACH PM 5TH & CHESAPEAKE",
                        "stop_url": "",
                        "wheelchair_boarding": "0",
                        "zone_id": ""
                    }
                }
            ],
            "name": "NORTH BEACH PM 5TH & CHESAPEAKE",
            "onestopId": "s-dqcs4qqdmg-northbeachpm5th~chesapeake",
            "properties": {},
            "servedBy": [
                "o-dqc-marylandtransitadministration"
            ],
            "tags": {},
            "type": "Feature"
        }
    ],
    "prefix": "dqcs4",
    "properties": {},
    "type": "FeatureCollection"
}