{
    "features": [
        {
            "geometry": {
                "coordinates": [
                    -76.779012,
                    39.295087
                ],
                "type": "Point"
            },
            "identifiers": [
                {
                    "identifier": "f-mtamaryland-s-7533",
                    "tags": {
                        "location_type": "",
                        "parent_station": "",
                        "stop_code": "7533",
                        "stop_desc": "BALTIMORE NATIONAL PIKE at PATAPSCO STATE PARK",
                        "stop_id": "7533",
                        "stop_lat": "39.295087",
                        "stop_lon": "-76.779012",
                        "stop_name": "RT. 40 & PATAPSCO",
                        "stop_url": "",
                        "wheelchair_boarding": "0",
                        "zone_id": ""
                    }
                }
            ],
            "name": "RT. 40 & PATAPSCO",
            "onestopId": "s-dqcrsc7nrr-rt40~patapsco",
            "properties": {},
            "servedBy": [
                "o-dqc-marylandtransitadministration"
            ],
            "tags": {},
            "type": "Feature"
        },
        {
            "geometry": {
                "coordinates": [
                    -76.77936,
                    39.295606
                ],
                "type": "Point"
            },
            "identifiers": [
                {
                    "identifier": "f-mtamaryland-s-7557",
                    "tags": {
                        "location_type": "",
                        "parent_station": "",
                        "stop_code": "7557",
                        "stop_desc": "BALTIMORE NATIONAL PIKE at PATAPSCO RIVER wb",
                        "stop_id": "7557",
                        "stop_lat": "39.295606",
                        "stop_lon": "-76.77936",
                        "stop_name": "BALT NAT PIKE & PATAPSCO RIVER wb",
                        "stop_url": "",
                        "wheelchair_boarding": "0",
                        "zone_id": ""
                    }
                }
            ],
            "name": "BALT NAT PIKE & PATAPSCO RIVER wb",
            "onestopId": "s-dqcrscdcrp-baltnatpike~patapscoriverwb",
            "properties": {},
            "servedBy": [
                "o-dqc-marylandtransitadministration"
            ],
            "tags": {},
            "type": "Feature"
        }
    ],
    "prefix": "dqcrs",
    "properties": {},
    "type": "FeatureCollection"
}