{
    "features": [
        {
            "geometry": {
                "coordinates": [
                    -77.269474,
                    39.172595
                ],
                "type": "Point"
            },
            "identifiers": [
                {
                    "identifier": "f-mtamaryland-s-11950",
                    "tags": {
                        "location_type": "",
                        "parent_station": "",
                        "stop_code": "11950",
                        "stop_desc": "GERMANTOWN at MARC STATION eb",
                        "stop_id": "11950",
                        "stop_lat": "39.172595",
                        "stop_lon": "-77.269474",
                        "stop_name": "GERMANTOWN MARC eb",
                        "stop_url": "",
                        "wheelchair_boarding": "0",
                        "zone_id": ""
                    }
                }
            ],
            "name": "GERMANTOWN MARC eb",
            "onestopId": "s-dqcncenhfu-germantownmarceb",
            "properties": {},
            "servedBy": [
                "o-dqc-marylandtransitadministration"
            ],
            "tags": {},
            "type": "Feature"
        },
        {
            "geometry": {
                "coordinates": [
                    -77.269566,
                    39.172523
                ],
                "type": "Point"
            },
            "identifiers": [
                {
                    "identifier": "f-mtamaryland-s-11966",
                    "tags": {
                        "location_type": "",
                        "parent_station": "",
                        "stop_code": "11966",
                        "stop_desc": "GERMANTOWN at MARC STATION wb",
                        "stop_id": "11966",
                        "stop_lat": "39.172523",
                        "stop_lon": "-77.269566",
                        "stop_name": "GERMANTOWN MARC wb",
                        "stop_url": "",
                        "wheelchair_boarding": "0",
                        "zone_id": ""
                    }
                }
            ],
            "name": "GERMANTOWN MARC wb",
            "onestopId": "s-dqcncenh2x-germantownmarcwb",
            "properties": {},
            "servedBy": [
                "o-dqc-marylandtransitadministration"
            ],
            "tags": {},
            "type": "Feature"
        }
    ],
    "prefix": "dqcnc",
    "properties": {},
    "type": "FeatureCollection"
}