{
    "features": [
        {
            "geometry": {
                "coordinates": [
                    -77.081307,
                    38.773491
                ],
                "type": "Point"
            },
            "identifiers": [
                {
                    "identifier": "f-dqc-wmata-s-28583",
                    "tags": {
                        "stop_code": "5001818",
                        "stop_desc": "",
                        "stop_id": "28583",
                        "stop_lat": "38.773491",
                        "stop_lon": "-77.081307",
                        "stop_name": "RT 1 RICHMOND HWY & SOUTHGATE DR",
                        "zone_id": "0"
                    }
                }
            ],
            "name": "RT 1 RICHMOND HWY & SOUTHGATE DR",
            "onestopId": "s-dqchtfrpgq-rt1richmond~southgate",
            "properties": {},
            "servedBy": [
                "o-dqc-met"
            ],
            "tags": {},
            "type": "Feature"
        },
        {
            "geometry": {
                "coordinates": [
                    -77.080878,
                    38.773505
                ],
                "type": "Point"
            },
            "identifiers": [
                {
                    "identifier": "f-dqc-wmata-s-28600",
                    "tags": {
                        "stop_code": "5001835",
                        "stop_desc": "",
                        "stop_id": "28600",
                        "stop_lat": "38.773505",
                        "stop_lon": "-77.080878",
                        "stop_name": "RT 1 RICHMOND HWY & BEDDOO ST",
                        "zone_id": "0"
                    }
                }
            ],
            "name": "RT 1 RICHMOND HWY & BEDDOO ST",
            "onestopId": "s-dqchtfx2j3-rt1richmond~beddoo",
            "properties": {},
            "servedBy": [
                "o-dqc-met"
            ],
            "tags": {},
            "type": "Feature"
        }
    ],
    "prefix": "dqcht",
    "properties": {},
    "type": "FeatureCollection"
}