{
    "features": [
        {
            "geometry": {
                "coordinates": [
                    -77.730548,
                    39.324586
                ],
                "type": "Point"
            },
            "identifiers": [
                {
                    "identifier": "f-dq-mtamaryland-s-11974",
                    "tags": {
                        "location_type": "",
                        "parent_station": "",
                        "stop_code": "11974",
                        "stop_desc": "HARPERS FERRY W VA at MARC STATION wb",
                        "stop_id": "11974",
                        "stop_lat": "39.324586",
                        "stop_lon": "-77.730548",
                        "stop_name": "HARPERS FERRY W VA MARC wb",
                        "stop_url": "",
                        "wheelchair_boarding": "0",
                        "zone_id": ""
                    }
                }
            ],
            "name": "HARPERS FERRY W VA MARC wb",
            "onestopId": "s-dqbxxny66f-harpersferrywvamarcwb",
            "properties": {},
            "servedBy": [
                "o-dqc-marylandtransitadministration"
            ],
            "tags": {},
            "type": "Feature"
        },
        {
            "geometry": {
                "coordinates": [
                    -77.73057,
                    39.324496
                ],
                "type": "Point"
            },
            "identifiers": [
                {
                    "identifier": "f-dq-mtamaryland-s-11942",
                    "tags": {
                        "location_type": "",
                        "parent_station": "",
                        "stop_code": "11942",
                        "stop_desc": "HARPERS FERRY W VA at MARC STATION eb",
                        "stop_id": "11942",
                        "stop_lat": "39.324496",
                        "stop_lon": "-77.73057",
                        "stop_name": "HARPERS FERRY W VA MARC eb",
                        "stop_url": "",
                        "wheelchair_boarding": "0",
                        "zone_id": ""
                    }
                }
            ],
            "name": "HARPERS FERRY W VA MARC eb",
            "onestopId": "s-dqbxxny3f3-harpersferrywvamarceb",
            "properties": {},
            "servedBy": [
                "o-dqc-marylandtransitadministration"
            ],
            "tags": {},
            "type": "Feature"
        }
    ],
    "prefix": "dqbxx",
    "properties": {},
    "type": "FeatureCollection"
}