{
    "features": [
        {
            "geometry": {
                "coordinates": [
                    -76.729059,
                    39.15492
                ],
                "type": "Point"
            },
            "identifiers": [
                {
                    "identifier": "f-mtamaryland-s-13536",
                    "tags": {
                        "location_type": "",
                        "parent_station": "",
                        "stop_code": "13536",
                        "stop_desc": "",
                        "stop_id": "13536",
                        "stop_lat": "39.15492",
                        "stop_lon": "-76.729059",
                        "stop_name": "ARUNDEL MILLS CIR & ARUNDEL MILLS C",
                        "stop_url": "",
                        "wheelchair_boarding": "0",
                        "zone_id": ""
                    }
                }
            ],
            "name": "ARUNDEL MILLS CIR & ARUNDEL MILLS C",
            "onestopId": "s-dqcqtzztgq-arundelmillscir~arundelmillsc",
            "properties": {},
            "servedBy": [
                "o-dqc-marylandtransitadministration"
            ],
            "tags": {},
            "type": "Feature"
        },
        {
            "geometry": {
                "coordinates": [
                    -76.770766,
                    39.112066
                ],
                "type": "Point"
            },
            "identifiers": [
                {
                    "identifier": "f-mtamaryland-s-13509",
                    "tags": {
                        "location_type": "",
                        "parent_station": "",
                        "stop_code": "13509",
                        "stop_desc": "DENNIS RD at BRIARWOOD DR",
                        "stop_id": "13509",
                        "stop_lat": "39.112066",
                        "stop_lon": "-76.770766",
                        "stop_name": "NSA Visitor Control Center",
                        "stop_url": "",
                        "wheelchair_boarding": "0",
                        "zone_id": ""
                    }
                }
            ],
            "name": "NSA Visitor Control Center",
            "onestopId": "s-dqcqt01hr3-nsavisitorcontrol",
            "properties": {},
            "servedBy": [
                "o-dqc-marylandtransitadministration"
            ],
            "tags": {},
            "type": "Feature"
        }
    ],
    "prefix": "dqcqt",
    "properties": {},
    "type": "FeatureCollection"
}