{
    "features": [
        {
            "geometry": {
                "coordinates": [
                    -70.688375,
                    41.980206
                ],
                "type": "Point"
            },
            "identifiers": [
                {
                    "identifier": "f-drt-mbta-s-Plymouth",
                    "tags": {
                        "location_type": "0",
                        "parent_station": "",
                        "stop_code": "",
                        "stop_desc": "",
                        "stop_id": "Plymouth",
                        "stop_lat": "41.980206",
                        "stop_lon": "-70.688375",
                        "stop_name": "Plymouth",
                        "stop_url": "",
                        "wheelchair_boarding": "1",
                        "zone_id": ""
                    }
                }
            ],
            "name": "Plymouth",
            "onestopId": "s-drmwz6q23m-plymouth",
            "properties": {},
            "servedBy": [
                "o-drt-mbta"
            ],
            "tags": {},
            "type": "Feature"
        }
    ],
    "prefix": "drmwz",
    "properties": {},
    "type": "FeatureCollection"
}