{
    "features": [
        {
            "geometry": {
                "coordinates": [
                    -71.052288,
                    42.495543
                ],
                "type": "Point"
            },
            "identifiers": [
                {
                    "identifier": "f-mbta-s-74910",
                    "tags": {
                        "location_type": "0",
                        "parent_station": "",
                        "stop_code": "74910",
                        "stop_desc": "",
                        "stop_id": "74910",
                        "stop_lat": "42.495543",
                        "stop_lon": "-71.052288",
                        "stop_name": "Farm St @ Nahant St - Wakefield HS",
                        "stop_url": "",
                        "wheelchair_boarding": "0",
                        "zone_id": ""
                    }
                }
            ],
            "name": "Farm St @ Nahant St - Wakefield HS",
            "onestopId": "s-drt3z0j63x-farm~nahantwakefieldhs",
            "properties": {},
            "servedBy": [
                "o-drt-mbta"
            ],
            "tags": {},
            "type": "Feature"
        }
    ],
    "prefix": "drt3z",
    "properties": {},
    "type": "FeatureCollection"
}