{
    "features": [
        {
            "geometry": {
                "coordinates": [
                    -71.358051,
                    42.457147
                ],
                "type": "Point"
            },
            "identifiers": [
                {
                    "identifier": "f-drt-mbta-s-Concord",
                    "tags": {
                        "location_type": "0",
                        "parent_station": "",
                        "stop_code": "",
                        "stop_desc": "",
                        "stop_id": "Concord",
                        "stop_lat": "42.457147",
                        "stop_lon": "-71.358051",
                        "stop_name": "Concord",
                        "stop_url": "",
                        "wheelchair_boarding": "2",
                        "zone_id": ""
                    }
                }
            ],
            "name": "Concord",
            "onestopId": "s-drt381nduc-concord",
            "properties": {},
            "servedBy": [
                "o-drt-mbta"
            ],
            "tags": {},
            "type": "Feature"
        }
    ],
    "prefix": "drt38",
    "properties": {},
    "type": "FeatureCollection"
}