{
    "features": [
        {
            "geometry": {
                "coordinates": [
                    -74.16375,
                    40.73454
                ],
                "type": "Point"
            },
            "identifiers": [
                {
                    "identifier": "f-dr5r-panynjpath-s-781719",
                    "tags": {
                        "location_type": "0",
                        "parent_station": "26733",
                        "platform_code": "",
                        "stop_code": "",
                        "stop_desc": "",
                        "stop_id": "781719",
                        "stop_lat": "40.73454",
                        "stop_lon": "-74.16375",
                        "stop_name": "Newark Penn Station (Platform H)",
                        "stop_timezone": "",
                        "stop_url": "",
                        "zone_id": ""
                    }
                }
            ],
            "name": "Newark Penn Station (Platform H)",
            "onestopId": "s-dr5r8r7xgk-newarkpennstationplatformh",
            "properties": {},
            "servedBy": [
                "o-dr5r-portauthoritytranshudsoncorporation"
            ],
            "tags": {},
            "type": "Feature"
        },
        {
            "geometry": {
                "coordinates": [
                    -74.16375,
                    40.73454
                ],
                "type": "Point"
            },
            "identifiers": [
                {
                    "identifier": "f-dr5r-panynjpath-s-781718",
                    "tags": {
                        "location_type": "0",
                        "parent_station": "26733",
                        "platform_code": "",
                        "stop_code": "",
                        "stop_desc": "",
                        "stop_id": "781718",
                        "stop_lat": "40.73454",
                        "stop_lon": "-74.16375",
                        "stop_name": "Newark Penn Station (Platform B)",
                        "stop_timezone": "",
                        "stop_url": "",
                        "zone_id": ""
                    }
                }
            ],
            "name": "Newark Penn Station (Platform B)",
            "onestopId": "s-dr5r8r7xgk-newarkpennstationplatformb",
            "properties": {},
            "servedBy": [
                "o-dr5r-portauthoritytranshudsoncorporation"
            ],
            "tags": {},
            "type": "Feature"
        }
    ],
    "prefix": "dr5r8",
    "properties": {},
    "type": "FeatureCollection"
}