{
    "features": [
        {
            "geometry": {
                "coordinates": [
                    -77.405583,
                    39.411719
                ],
                "type": "Point"
            },
            "identifiers": [
                {
                    "identifier": "f-dq-mtamaryland-s-FRDRK_TRAN_CTR",
                    "tags": {
                        "location_type": "",
                        "parent_station": "",
                        "stop_code": "",
                        "stop_desc": "MARC Train Service and TransIT service available",
                        "stop_id": "FRDRK_TRAN_CTR",
                        "stop_lat": "39.411719",
                        "stop_lon": "-77.405583",
                        "stop_name": "Frederick Transit Center",
                        "stop_url": "",
                        "wheelchair_boarding": "",
                        "zone_id": ""
                    }
                }
            ],
            "name": "Frederick Transit Center",
            "onestopId": "s-dr0bnwdvzh-fredericktransit",
            "properties": {},
            "servedBy": [
                "o-dq-mtaofficeoflocaltransitsupport"
            ],
            "tags": {},
            "type": "Feature"
        }
    ],
    "prefix": "dr0bn",
    "properties": {},
    "type": "FeatureCollection"
}