{
    "features": [
        {
            "geometry": {
                "coordinates": [
                    -70.838052,
                    42.244251
                ],
                "type": "Point"
            },
            "identifiers": [
                {
                    "identifier": "f-mbta-s-Cohasset",
                    "tags": {
                        "location_type": "0",
                        "parent_station": "",
                        "stop_code": "",
                        "stop_desc": "",
                        "stop_id": "Cohasset",
                        "stop_lat": "42.244251",
                        "stop_lon": "-70.838052",
                        "stop_name": "Cohasset",
                        "stop_url": "",
                        "wheelchair_boarding": "1",
                        "zone_id": ""
                    }
                }
            ],
            "name": "Cohasset",
            "onestopId": "s-drt8k4369g-cohasset",
            "properties": {},
            "servedBy": [
                "o-drt-mbta"
            ],
            "tags": {},
            "type": "Feature"
        }
    ],
    "prefix": "drt8k",
    "properties": {},
    "type": "FeatureCollection"
}