{
    "features": [
        {
            "geometry": {
                "coordinates": [
                    -71.524371,
                    42.267024
                ],
                "type": "Point"
            },
            "identifiers": [
                {
                    "identifier": "f-mbta-s-Southborough",
                    "tags": {
                        "location_type": "0",
                        "parent_station": "",
                        "stop_code": "",
                        "stop_desc": "",
                        "stop_id": "Southborough",
                        "stop_lat": "42.267024",
                        "stop_lon": "-71.524371",
                        "stop_name": "Southborough",
                        "stop_url": "",
                        "wheelchair_boarding": "1",
                        "zone_id": ""
                    }
                }
            ],
            "name": "Southborough",
            "onestopId": "s-drt0kqmx32-southborough",
            "properties": {},
            "servedBy": [
                "o-drt-mbta"
            ],
            "tags": {},
            "type": "Feature"
        }
    ],
    "prefix": "drt0k",
    "properties": {},
    "type": "FeatureCollection"
}