{
    "features": [
        {
            "geometry": {
                "coordinates": [
                    -71.28944,
                    42.457495
                ],
                "type": "Point"
            },
            "identifiers": [
                {
                    "identifier": "f-mbta-s-86178",
                    "tags": {
                        "location_type": "0",
                        "parent_station": "",
                        "stop_code": "86178",
                        "stop_desc": "",
                        "stop_id": "86178",
                        "stop_lat": "42.457495",
                        "stop_lon": "-71.28944",
                        "stop_name": "Hanscom Field Dr @ Old Bedford Rd",
                        "stop_url": "",
                        "wheelchair_boarding": "0",
                        "zone_id": ""
                    }
                }
            ],
            "name": "Hanscom Field Dr @ Old Bedford Rd",
            "onestopId": "s-drt39c0sgd-hanscomfield~oldbedford",
            "properties": {},
            "servedBy": [
                "o-drt-mbta"
            ],
            "tags": {},
            "type": "Feature"
        },
        {
            "geometry": {
                "coordinates": [
                    -71.289581,
                    42.457368
                ],
                "type": "Point"
            },
            "identifiers": [
                {
                    "identifier": "f-mbta-s-86180",
                    "tags": {
                        "location_type": "0",
                        "parent_station": "",
                        "stop_code": "86180",
                        "stop_desc": "",
                        "stop_id": "86180",
                        "stop_lat": "42.457368",
                        "stop_lon": "-71.289581",
                        "stop_name": "Hanscom Field Dr @ Old Bedford Rd",
                        "stop_url": "",
                        "wheelchair_boarding": "0",
                        "zone_id": ""
                    }
                }
            ],
            "name": "Hanscom Field Dr @ Old Bedford Rd",
            "onestopId": "s-drt39c0s07-hanscomfield~oldbedford",
            "properties": {},
            "servedBy": [
                "o-drt-mbta"
            ],
            "tags": {},
            "type": "Feature"
        },
        {
            "geometry": {
                "coordinates": [
                    -71.291173,
                    42.462813
                ],
                "type": "Point"
            },
            "identifiers": [
                {
                    "identifier": "f-mbta-s-86179",
                    "tags": {
                        "location_type": "0",
                        "parent_station": "",
                        "stop_code": "86179",
                        "stop_desc": "",
                        "stop_id": "86179",
                        "stop_lat": "42.462813",
                        "stop_lon": "-71.291173",
                        "stop_name": "Civil Air Terminal",
                        "stop_url": "",
                        "wheelchair_boarding": "0",
                        "zone_id": ""
                    }
                }
            ],
            "name": "Civil Air Terminal",
            "onestopId": "s-drt39dp7g6-civilairterminal",
            "properties": {},
            "servedBy": [
                "o-drt-mbta"
            ],
            "tags": {},
            "type": "Feature"
        }
    ],
    "prefix": "drt39",
    "properties": {},
    "type": "FeatureCollection"
}