{
    "features": [
        {
            "geometry": {
                "coordinates": [
                    -71.391797,
                    42.283064
                ],
                "type": "Point"
            },
            "identifiers": [
                {
                    "identifier": "f-mbta-s-West Natick",
                    "tags": {
                        "location_type": "0",
                        "parent_station": "",
                        "stop_code": "",
                        "stop_desc": "",
                        "stop_id": "West Natick",
                        "stop_lat": "42.283064",
                        "stop_lon": "-71.391797",
                        "stop_name": "West Natick",
                        "stop_url": "",
                        "wheelchair_boarding": "1",
                        "zone_id": ""
                    }
                }
            ],
            "name": "West Natick",
            "onestopId": "s-drt0x3qhdw-westnatick",
            "properties": {},
            "servedBy": [
                "o-drt-mbta"
            ],
            "tags": {},
            "type": "Feature"
        }
    ],
    "prefix": "drt0x",
    "properties": {},
    "type": "FeatureCollection"
}