{
    "features": [
        {
            "geometry": {
                "coordinates": [
                    -71.011004,
                    42.060951
                ],
                "type": "Point"
            },
            "identifiers": [
                {
                    "identifier": "f-drt-mbta-s-Campello",
                    "tags": {
                        "location_type": "0",
                        "parent_station": "",
                        "stop_code": "",
                        "stop_desc": "",
                        "stop_id": "Campello",
                        "stop_lat": "42.060951",
                        "stop_lon": "-71.011004",
                        "stop_name": "Campello",
                        "stop_url": "",
                        "wheelchair_boarding": "1",
                        "zone_id": ""
                    }
                }
            ],
            "name": "Campello",
            "onestopId": "s-drmx20gqg9-campello",
            "properties": {},
            "servedBy": [
                "o-drt-mbta"
            ],
            "tags": {},
            "type": "Feature"
        }
    ],
    "prefix": "drmx2",
    "properties": {},
    "type": "FeatureCollection"
}