{
    "features": [
        {
            "geometry": {
                "coordinates": [
                    -70.923411,
                    42.082749
                ],
                "type": "Point"
            },
            "identifiers": [
                {
                    "identifier": "f-mbta-s-Whitman",
                    "tags": {
                        "location_type": "0",
                        "parent_station": "",
                        "stop_code": "",
                        "stop_desc": "",
                        "stop_id": "Whitman",
                        "stop_lat": "42.082749",
                        "stop_lon": "-70.923411",
                        "stop_name": "Whitman",
                        "stop_url": "",
                        "wheelchair_boarding": "1",
                        "zone_id": ""
                    }
                }
            ],
            "name": "Whitman",
            "onestopId": "s-drmx6hgju8-whitman",
            "properties": {},
            "servedBy": [
                "o-drt-mbta"
            ],
            "tags": {},
            "type": "Feature"
        }
    ],
    "prefix": "drmx6",
    "properties": {},
    "type": "FeatureCollection"
}