{
    "features": [
        {
            "geometry": {
                "coordinates": [
                    -71.325344,
                    42.414229
                ],
                "type": "Point"
            },
            "identifiers": [
                {
                    "identifier": "f-drt-mbta-s-Lincoln",
                    "tags": {
                        "location_type": "0",
                        "parent_station": "",
                        "stop_code": "",
                        "stop_desc": "",
                        "stop_id": "Lincoln",
                        "stop_lat": "42.414229",
                        "stop_lon": "-71.325344",
                        "stop_name": "Lincoln",
                        "stop_url": "",
                        "wheelchair_boarding": "2",
                        "zone_id": ""
                    }
                }
            ],
            "name": "Lincoln",
            "onestopId": "s-drt32cq2z1-lincoln",
            "properties": {},
            "servedBy": [
                "o-drt-mbta"
            ],
            "tags": {},
            "type": "Feature"
        }
    ],
    "prefix": "drt32",
    "properties": {},
    "type": "FeatureCollection"
}