{
    "features": [
        {
            "geometry": {
                "coordinates": [
                    -75.760658,
                    39.691527
                ],
                "type": "Point"
            },
            "identifiers": [
                {
                    "identifier": "f-dq-mtamaryland-s-NEWARK",
                    "tags": {
                        "location_type": "",
                        "parent_station": "",
                        "stop_code": "",
                        "stop_desc": "Parking Lot 6",
                        "stop_id": "NEWARK",
                        "stop_lat": "39.691527",
                        "stop_lon": "-75.760658",
                        "stop_name": "Univ of Deleware",
                        "stop_url": "",
                        "wheelchair_boarding": "",
                        "zone_id": ""
                    }
                }
            ],
            "name": "Univ of Deleware",
            "onestopId": "s-dr41u18gbs-univofdeleware",
            "properties": {},
            "servedBy": [
                "o-dq-mtaofficeoflocaltransitsupport"
            ],
            "tags": {},
            "type": "Feature"
        }
    ],
    "prefix": "dr41u",
    "properties": {},
    "type": "FeatureCollection"
}