{
    "features": [
        {
            "geometry": {
                "coordinates": [
                    -70.934405,
                    42.107156
                ],
                "type": "Point"
            },
            "identifiers": [
                {
                    "identifier": "f-mbta-s-Abington",
                    "tags": {
                        "location_type": "0",
                        "parent_station": "",
                        "stop_code": "",
                        "stop_desc": "",
                        "stop_id": "Abington",
                        "stop_lat": "42.107156",
                        "stop_lon": "-70.934405",
                        "stop_name": "Abington",
                        "stop_url": "",
                        "wheelchair_boarding": "1",
                        "zone_id": ""
                    }
                }
            ],
            "name": "Abington",
            "onestopId": "s-drmx9c75uw-abington",
            "properties": {},
            "servedBy": [
                "o-drt-mbta"
            ],
            "tags": {},
            "type": "Feature"
        }
    ],
    "prefix": "drmx9",
    "properties": {},
    "type": "FeatureCollection"
}