{
    "features": [
        {
            "geometry": {
                "coordinates": [
                    -77.567294,
                    39.492448
                ],
                "type": "Point"
            },
            "identifiers": [
                {
                    "identifier": "f-mtamaryland-s-12763",
                    "tags": {
                        "location_type": "",
                        "parent_station": "",
                        "stop_code": "12763",
                        "stop_desc": "VENTRIE CT at MYERSVILLE RD",
                        "stop_id": "12763",
                        "stop_lat": "39.492448",
                        "stop_lon": "-77.567294",
                        "stop_name": "MEYERSVILLE PARK & RIDE",
                        "stop_url": "",
                        "wheelchair_boarding": "0",
                        "zone_id": ""
                    }
                }
            ],
            "name": "MEYERSVILLE PARK & RIDE",
            "onestopId": "s-dr0bdvmhpj-meyersvillepark~ride",
            "properties": {},
            "servedBy": [
                "o-dqc-marylandtransitadministration"
            ],
            "tags": {},
            "type": "Feature"
        }
    ],
    "prefix": "dr0bd",
    "properties": {},
    "type": "FeatureCollection"
}